{
  "passage": "1THESSALONIANS.4.13-1THESSALONIANS.4.18",
  "text": "13 But we do not want you to be uninformed,\n     brothers,\n     about those who are asleep,\n     that you may not grieve as others do\n       who have no hope.\n14 For since we believe that Jesus died\n       and rose again,\n     even so,\n       through Jesus,\n     God will bring with him those who have fallen asleep.\n15 For this we declare to you\n       by a word from the Lord,\n     that we who are alive,\n     who are left\n       until the coming of the Lord,\n     will not precede those who have fallen asleep.\n16 For the Lord himself will descend\n       from heaven\n     with a cry of command,\n     with the voice of an archangel,\n     and with the sound of the trumpet of God.\n     And the dead in Christ will rise first.\n  17 Then we who are alive,\n       who are left,\n     will be caught up together with them\n       in the clouds\n     to meet the Lord in the air,\n     and so we will always be with the Lord.\n18 Therefore encourage one another\n     with these words.",
  "observe": {
    "people": [
      "we = Paul, Silvanus, Timothy",
      "you = Thessalonians",
      "those who are asleep",
      "others who have no hope",
      "Jesus",
      "God",
      "Lord",
      "we who are alive",
      "archangel",
      "Christ",
      "them",
      "one another"
    ],
    "nouns": [
      "hope",
      "word",
      "the coming",
      "heaven",
      "cry",
      "command",
      "voice",
      "sound",
      "trumpet",
      "clouds",
      "air",
      "words"
    ],
    "adjectives": [
      "uninformed",
      "asleep",
      "again",
      "from",
      "alive",
      "left",
      "with",
      "always"
    ],
    "actions": [
      "grieve",
      "believe",
      "died",
      "rose",
      "bring",
      "fallen",
      "declare",
      "coming",
      "precede",
      "descend",
      "caught up",
      "meet",
      "be",
      "encourage"
    ],
    "persons": {
      "God": [
        "Jesus died and rose again",
        "will bring with him those who have fallen asleep",
        "gave a word to Paul regarding those who have fallen asleep",
        "the Lord is coming",
        "the Lord will descend from heaven",
        "the Lord will descend with a cry of command",
        "the Lord will descend with the voice of an archangel",
        "the Lord will descend with the sound of the trumpet of God",
        "will meet His people in the air at His coming",
        "will always be with us after His coming"
      ],
      "Author": [],
      "Audience": []
    },
    "definitions": {}
  },
  "interpret": {
    "mainPoint": "",
    "keywords": {},
    "points": [],
    "titles": [],
    "emotions": {},
    "unwisdom": [
      {
        "passage": "",
        "saying": "",
        "comment": "",
        "chapter": ""
      }
    ],
    "expound": [
      {
        "one": "",
        "two": "",
        "three": "",
        "four": ""
      }
    ]
  },
  "application": {
    "conversation": [
      {
        "question": ""
      }
    ],
    "ACTS": {
      "adoration": [],
      "confession": [],
      "thanks": [],
      "supplication": []
    },
    "integrity": [
      {
        "question": ""
      }
    ]
  }
}